[
	{
		"name": "Full Stack Web Development Bootcamp",
		"description": "An intensive program to learn full-stack web development from scratch. Covers front-end and back-end technologies including HTML, CSS, JavaScript, React, Node.js, and more.",
		"duration": 12,
		"level": "Intermediate",
		"website": "https://www.examplebootcamp.com",
		"onlineAvailable": true,
		"electronicMedium": "zoom",
		"mediumLink": "https://zoom.us/meeting/123456789",
		"category": ["Web Development", "Programming"],
		"averageRating": 4.5,
		"costType": "paid",
		"price": 1200,
		"startDate": "2024-09-01T00:00:00.000Z",
		"endDate": "2024-11-30T00:00:00.000Z",
		"photo": "full-stack-web-dev.jpg",
		"user": "60c72b2f9b1e8d3f2d8f56b7"
	},
	{
		"name": "Data Science Mastery",
		"description": "A comprehensive bootcamp to master data science. Topics include Python, machine learning, data visualization, and statistical analysis.",
		"duration": 16,
		"level": "Advanced",
		"website": "https://www.datasciencemastery.com",
		"onlineAvailable": true,
		"electronicMedium": "google meet",
		"mediumLink": "https://meet.google.com/abc-defg-hij",
		"category": ["Data Science", "Machine Learning"],
		"averageRating": 4.8,
		"costType": "paid",
		"price": 1500,
		"startDate": "2024-10-01T00:00:00.000Z",
		"endDate": "2025-01-15T00:00:00.000Z",
		"photo": "data-science-mastery.jpg",
		"user": "60c72b2f9b1e8d3f2d8f56b8"
	},
	{
		"name": "UI/UX Design Fundamentals",
		"description": "Learn the basics of UI/UX design, including design principles, user research, and prototyping techniques.",
		"duration": 8,
		"level": "Beginner",
		"website": "https://www.uiuxdesignfundamentals.com",
		"onlineAvailable": false,
		"venue": "123 Design Street, Design City",
		"address": "123 Design Street, Design City",
		"category": ["UI/UX", "Design"],
		"averageRating": 4.2,
		"costType": "free",
		"price": null,
		"startDate": "2024-08-15T00:00:00.000Z",
		"endDate": "2024-10-15T00:00:00.000Z",
		"photo": "ui-ux-design-fundamentals.jpg",
		"user": "60c72b2f9b1e8d3f2d8f56b9"
	}
]
